gekito/__init__.py
gekito/config.py
gekito/group.py
gekito-0.0.2.dist-info/LICENSE
gekito-0.0.2.dist-info/METADATA
gekito-0.0.2.dist-info/WHEEL
gekito-0.0.2.dist-info/RECORD
